{"\/":255,"\/kiem-dinh":195,"\/kiem-dinh\/highcharts-demo":28,"\/quan-ly-anh-san-pham":24,"\/home":4,"\/kiem-dinh\/quan-ly-anh-san-pham":34,"\/kiem-dinh-thiet-bi":96,"\/huan-luyen-an-toan":35,"\/kiem-dinh-thiet-bi\/kiem-dinh-van-an-toan":26,"\/quy-trinh-kiem-dinh":10,"\/tin-tuc":4,"\/kiem-dinh\/tim-hieu-ve-quy-trinh-kiem-dinh-ky-thuat-an-toan":8,"\/kiem-dinh-thiet-bi\/kiem-dinh-an-toan-xe-nang-thiet-bi-nang":5,"\/kiem-dinh-thiet-bi\/kiem-dinh-he-thong-lanh":2,"\/kiem-dinh-thiet-bi\/kiem-dinh-be-bon-thiet-bi-chua":3,"\/kiem-dinh-thiet-bi\/kiem-dinh-noi-hoi-lo-hoi":26,"\/kiem-dinh-thiet-bi\/kiem-dinh-van-thang":2}